MANIFEST.in
README.md
dependencies.json
setup.py
src/databricks_runtime.egg-info/PKG-INFO
src/databricks_runtime.egg-info/SOURCES.txt
src/databricks_runtime.egg-info/dependency_links.txt
src/databricks_runtime.egg-info/requires.txt
src/databricks_runtime.egg-info/top_level.txt
src/runtime/__init__.py
src/runtime/runtime-metadata.json
src/runtime/settings.py