Metadata-Version: 2.1
Name: databricks-runtime
Version: 7.3.dev4
Summary: Databricks LTS Python Runtime
Home-page: https://github.com/rhdzmota/databricks-runtime
Author: rhdzmota
Author-email: contact@rhdzmota.com
License: MIT
Platform: UNKNOWN
Classifier: Programming Language :: Python :: 3.7
Requires-Python: >=3.7, <3.8
